lysis_curve.py
lysis_curve-1.12.dist-info/LICENSE
lysis_curve-1.12.dist-info/METADATA
lysis_curve-1.12.dist-info/WHEEL
lysis_curve-1.12.dist-info/top_level.txt
lysis_curve-1.12.dist-info/RECORD
