Metadata-Version: 2.1
Name: lysis-curve
Version: 1.12
Summary: Lysis curve package
Home-page: https://github.com/jakechamblee/Lysis-curve
Author: Jake Chamblee
Author-email: jchamblee1995@gmail.com
License: MIT
Download-URL: https://github.com/jakechamblee/lysis-curve/archive/refs/tags/1.12.tar.gz
Keywords: bacteriophage,phage,growth curve,lysis,graphing
Platform: UNKNOWN
Classifier: Programming Language :: Python :: 3
Classifier: License :: OSI Approved :: MIT License
Classifier: Operating System :: OS Independent
Requires-Python: >=3.6
License-File: LICENSE
Requires-Dist: pandas
Requires-Dist: plotly
Requires-Dist: kaleido
Requires-Dist: requests
